fastl2lir/__init__.py
fastl2lir/fastl2lir.py
fastl2lir-0.10.dist-info/LICENSE
fastl2lir-0.10.dist-info/METADATA
fastl2lir-0.10.dist-info/WHEEL
fastl2lir-0.10.dist-info/top_level.txt
fastl2lir-0.10.dist-info/RECORD
